dsnetclient/__init__.py
dsnetclient/api.py
dsnetclient/async_cmd.py
dsnetclient/index.py
dsnetclient/main.py
dsnetclient/models.py
dsnetclient/mutually_exclusive_click.py
dsnetclient/repository.py
test/__init__.py
test/server.py
test/server_oauth2.py
test/test_api.py
test/test_api_auth.py
test/test_api_integration.py
test/test_lucene.py
test/test_repository.py
test/test_server.py
test/test_server_oauth2.py
test/test_utils.py
datashare_network_client-0.4.0.dist-info/LICENSE.txt
datashare_network_client-0.4.0.dist-info/METADATA
datashare_network_client-0.4.0.dist-info/WHEEL
datashare_network_client-0.4.0.dist-info/entry_points.txt
datashare_network_client-0.4.0.dist-info/top_level.txt
datashare_network_client-0.4.0.dist-info/RECORD
