Metadata-Version: 2.1
Name: datashare-network-client
Version: 0.4.0
Summary: Client Datashare Network Library
Home-page: https://github.com/ICIJ/datashare-network-client
License: UNKNOWN
Keywords: datashare,api,network,cryptography
Platform: UNKNOWN
Classifier: Programming Language :: Python :: 3
Classifier: Programming Language :: Python :: 3.6
Classifier: Programming Language :: Python :: 3.7
Classifier: Programming Language :: Python :: 3.8
Classifier: Intended Audience :: Developers
Classifier: License :: OSI Approved :: GNU Affero General Public License v3
Classifier: Operating System :: OS Independent
Classifier: Topic :: Security :: Cryptography
Requires-Python: >=3.6
License-File: LICENSE.txt
Requires-Dist: Authlib (==1.0.0)
Requires-Dist: aioconsole (==0.4.1)
Requires-Dist: aiohttp (==3.8.1)
Requires-Dist: click (==8.0.4)
Requires-Dist: datashare-network-core (==0.13.0)
Requires-Dist: elasticsearch (==7.9.1)
Requires-Dist: httpx
Requires-Dist: sscred (==0.2.1)
